pandas_multi.py
pandas_multi-2019.3.12.dist-info/LICENSE
pandas_multi-2019.3.12.dist-info/METADATA
pandas_multi-2019.3.12.dist-info/WHEEL
pandas_multi-2019.3.12.dist-info/top_level.txt
pandas_multi-2019.3.12.dist-info/RECORD
