Metadata-Version: 2.1
Name: pandas-multi
Version: 2019.3.12
Summary: Read multiple csvs or Excel files as a single pandas DataFrame.
Home-page: https://github.com/bartbroere/pandas_multi/
Author: Bart Broere
Author-email: mail@bartbroere.eu
License: MIT License
Keywords: pandas readcsv readcsvs csv xls xlsx excel dataframe multiple multi
Platform: UNKNOWN
Classifier: License :: OSI Approved :: MIT License
Classifier: Programming Language :: Python :: 3 :: Only
Classifier: Programming Language :: Python :: 3.4
Classifier: Programming Language :: Python :: 3.5
Classifier: Programming Language :: Python :: 3.6
Classifier: Programming Language :: Python :: 3.7
Classifier: Programming Language :: Python :: 3.8
Classifier: Topic :: Utilities
Requires-Dist: pandas
